main.py
opcua_mcp-0.1.0.dist-info/licenses/LICENSE
opcua_mcp-0.1.0.dist-info/METADATA
opcua_mcp-0.1.0.dist-info/WHEEL
opcua_mcp-0.1.0.dist-info/top_level.txt
opcua_mcp-0.1.0.dist-info/RECORD
