Metadata-Version: 2.4
Name: opcua-mcp
Version: 0.1.0
Summary: An MCP server that connects AI agents to OPC UA-enabled industrial systems.
Requires-Python: >=3.13
License-File: LICENSE
Requires-Dist: asyncua>=1.1.5
Requires-Dist: mcp[cli]>=1.5.0
Dynamic: license-file
